folkol/yg.py
folkol.yg-0.0.16.dist-info/METADATA
folkol.yg-0.0.16.dist-info/RECORD
folkol.yg-0.0.16.dist-info/WHEEL
folkol.yg-0.0.16.dist-info/entry_points.txt
folkol.yg-0.0.16.dist-info/top_level.txt
